pyZlBusSdk/__init__.py
pyZlBusSdk/bleTest.py
pyZlBusSdk/pyZlBus.py
pyZlBusSdk/test.py
pyZlBusSdk/linux/libPyZlBusApi_py310.so
pyZlBusSdk/linux/libPyZlBusApi_py311.so
pyZlBusSdk/linux/libPyZlBusApi_py312.so
pyZlBusSdk/win/PyZlBusApi_py310.pyd
pyZlBusSdk/win/PyZlBusApi_py311.pyd
pyZlBusSdk/win/PyZlBusApi_py312.pyd
pyZlBusSdk-0.1.0.data/data/pyZlBusSdk/linux/libPyZlBusApi_py310.so
pyZlBusSdk-0.1.0.data/data/pyZlBusSdk/linux/libPyZlBusApi_py311.so
pyZlBusSdk-0.1.0.data/data/pyZlBusSdk/linux/libPyZlBusApi_py312.so
pyZlBusSdk-0.1.0.data/data/pyZlBusSdk/win/PyZlBusApi_py310.pyd
pyZlBusSdk-0.1.0.data/data/pyZlBusSdk/win/PyZlBusApi_py311.pyd
pyZlBusSdk-0.1.0.data/data/pyZlBusSdk/win/PyZlBusApi_py312.pyd
pyZlBusSdk-0.1.0.dist-info/METADATA
pyZlBusSdk-0.1.0.dist-info/WHEEL
pyZlBusSdk-0.1.0.dist-info/top_level.txt
pyZlBusSdk-0.1.0.dist-info/RECORD
